kagi_bridge_mcp/__init__.py
kagi_bridge_mcp/server.py
kagi_bridge_mcp-0.1.6.dist-info/METADATA
kagi_bridge_mcp-0.1.6.dist-info/WHEEL
kagi_bridge_mcp-0.1.6.dist-info/entry_points.txt
kagi_bridge_mcp-0.1.6.dist-info/licenses/LICENSE
kagi_bridge_mcp-0.1.6.dist-info/RECORD
