Metadata-Version: 2.4
Name: kagi-bridge-mcp
Version: 0.1.6
Summary: Kagi Bridge MCP Server
Project-URL: Homepage, https://github.com/waynexia/kagi-bridge-mcp
Project-URL: Issues, https://github.com/waynexia/kagi-bridge-mcp/issues
Author: Ruihang Xia
License-File: LICENSE
Requires-Python: >=3.12
Requires-Dist: mcp[cli]~=1.2.0
Requires-Dist: playwright>=1.36.0
Requires-Dist: pydantic>=2.10.3
Provides-Extra: dev
Requires-Dist: pytest-asyncio>=0.21.0; extra == 'dev'
Requires-Dist: pytest>=7.0.0; extra == 'dev'
